geovizir/__init__.py
geovizir/data.py
geovizir/dplyr.py
geovizir/features.py
geovizir/resources/__init__.py
geovizir/resources/ne_10m_admin_0_countries/__init__.py
geovizir/resources/ne_10m_admin_0_countries/ne_10m_admin_0_countries.README.html
geovizir/resources/ne_10m_admin_0_countries/ne_10m_admin_0_countries.VERSION.txt
geovizir/resources/ne_10m_admin_0_countries/ne_10m_admin_0_countries.cpg
geovizir/resources/ne_10m_admin_0_countries/ne_10m_admin_0_countries.dbf
geovizir/resources/ne_10m_admin_0_countries/ne_10m_admin_0_countries.prj
geovizir/resources/ne_10m_admin_0_countries/ne_10m_admin_0_countries.shp
geovizir/resources/ne_10m_admin_0_countries/ne_10m_admin_0_countries.shx
geovizir/resources/ne_10m_admin_1_states_provinces/__init__.py
geovizir/resources/ne_10m_admin_1_states_provinces/ne_10m_admin_1_states_provinces.README.html
geovizir/resources/ne_10m_admin_1_states_provinces/ne_10m_admin_1_states_provinces.VERSION.txt
geovizir/resources/ne_10m_admin_1_states_provinces/ne_10m_admin_1_states_provinces.cpg
geovizir/resources/ne_10m_admin_1_states_provinces/ne_10m_admin_1_states_provinces.dbf
geovizir/resources/ne_10m_admin_1_states_provinces/ne_10m_admin_1_states_provinces.prj
geovizir/resources/ne_10m_admin_1_states_provinces/ne_10m_admin_1_states_provinces.shp
geovizir/resources/ne_10m_admin_1_states_provinces/ne_10m_admin_1_states_provinces.shx
geovizir/resources/ne_110m_admin_0_countries/__init__.py
geovizir/resources/ne_110m_admin_0_countries/ne_110m_admin_0_countries.README.html
geovizir/resources/ne_110m_admin_0_countries/ne_110m_admin_0_countries.VERSION.txt
geovizir/resources/ne_110m_admin_0_countries/ne_110m_admin_0_countries.cpg
geovizir/resources/ne_110m_admin_0_countries/ne_110m_admin_0_countries.dbf
geovizir/resources/ne_110m_admin_0_countries/ne_110m_admin_0_countries.prj
geovizir/resources/ne_110m_admin_0_countries/ne_110m_admin_0_countries.shp
geovizir/resources/ne_110m_admin_0_countries/ne_110m_admin_0_countries.shx
geovizir-2.5.3.dist-info/METADATA
geovizir-2.5.3.dist-info/WHEEL
geovizir-2.5.3.dist-info/licenses/LICENSE
geovizir-2.5.3.dist-info/RECORD
