Metadata-Version: 2.4
Name: geovizir
Version: 2.5.3
Summary: Support package for geo visuals.
License: MIT
License-File: LICENSE
Author: Pascal Burkhard
Requires-Python: >=3.10,<4.0
Classifier: License :: OSI Approved :: MIT License
Classifier: Programming Language :: Python :: 3
Classifier: Programming Language :: Python :: 3.10
Classifier: Programming Language :: Python :: 3.11
Classifier: Programming Language :: Python :: 3.12
Classifier: Programming Language :: Python :: 3.13
Classifier: Programming Language :: Python :: 3.14
Requires-Dist: geopandas (>=0.14.1,<0.15.0)
Requires-Dist: pandas (>=2.1.4,<3.0.0)
Requires-Dist: pyproj (>=3.7.0,<4.0.0)
Requires-Dist: wbgapi (>=1.0.12,<2.0.0)
